{
    "rule_nr": "2.02.02.18",
    "name": {
        "nl": "@substitutionGroup MOET gebruikt worden op root <xs:element> die concepten zijn",
        "en": "@substitutionGroup MUST be used on root <xs:element> for concepts"
    },
    "explanation": {
        "nl": "XBRL voorgeschreven zijn het gebruik van:\n*xbrli:item\n*xbrli:tuple\n*xbrldt:dimensionItem\n*xbrldt:hypercubeItem \nDaarnaast heeft SBR er ook een aantal aangemaakt:\n*sbr:domainItem\n*sbr:domainMemberItem\n*sbr:primaryDomainItem\n*sbr:presentationItem\n*sbr:presentationTuple\n*sbr:specificationTuple",
        "en": null
    },
    "introduction_date": "2010/06/23",
    "related": "2.02.02.05, 2.02.02.19, 4.01.053",
    "error_message": {
        "nl": "//xs:element/@substitutionGroup MOET NIET gebruikt worden op non-XDT context content en typed dimensie elementen",
        "en": null
    },
    "nta_rule": true,
    "pe_rule": true,
    "section": "XML Schema - Concepten"
}