{
    "rule_nr": "2.03.08.10",
    "name": {
        "nl": "Een <link:label> inhoud MOET GEEN opmaak bevatten.",
        "en": "The content of <link:label> MUST NOT contain any rendering hints."
    },
    "explanation": {
        "nl": "Software die de labels wil gebruiken kan een probleem ondervinden bij de inzet van gestructureerde opmaak constructies als HTML en XHTML. Daarnaast is mogelijk virus code te verbergen in dergelijke constructies.",
        "en": null
    },
    "agreed_date": "2014/06/04",
    "error_message": {
        "nl": "<link:label> inhoud MOET GEEN opmaak bevatten",
        "en": null
    },
    "nta_rule": true,
    "pe_rule": true,
    "section": "XML Linkbase - Labels"
}