{
    "rule_nr": "3.02.08.06",
    "name": {
        "nl": "De naam van een datatype met <xs:restriction base=\"xbrli:*ItemType\">, voor generieke inzet, MOET het achtervoegsel 'ItemType' krijgen. Alleen datatypes ",
        "en": "The name of a datatype with met <xs:restriction base=\"xbrli:*ItemType\">, for generic use MUST have the suffix 'ItemType'"
    },
    "explanation": {
        "nl": "Verduidelijking toegevoegd naar aanleiding van discussie in WG NT:\nhttps://github.com/centrumvoorstandaarden/SBR_Werkgroep_NT/issues/6",
        "en": ""
    },
    "introduction_date": "2010/11/17",
    "error_message": {
        "nl": "",
        "en": ""
    },
    "nta_rule": false,
    "pe_rule": false,
    "testable": false,
    "section": "Naamgeving - Element type @name"
}