{
    "rule_nr": "3.02.08.05",
    "name": {
        "nl": "Een datatype voor generieke inzet, MOET de facets die aan het datatype zijn toegewezen opnemen in de naam conform tabel E",
        "en": "Datatypes for generic use MUST address the facets in their name conform table E"
    },
    "explanation": {
        "nl": "NA",
        "en": null
    },
    "introduction_date": "2012/05/01",
    "error_message": {
        "nl": null,
        "en": null
    },
    "nta_rule": true,
    "pe_rule": false,
    "references": "Naamgeving_hulptabellen#Tabel_E:_XML_Facets_die_in_de_datatype_naam_worden_opgenomen",
    "section": "Naamgeving - Element type @name"
}