{
    "rule_nr": "2.03.07.05",
    "name": {
        "nl": "Dimension-domain/@usable=\"false\" MOET gebruikt worden als het kind in de relatie in de sbr:domainItem substitutionGroup zit",
        "en": "Dimension-domain/@usable=\"false\" MUST be used if the child in the relationship is in the sbr:domainItem substitutionGroup"
    },
    "explanation": {
        "nl": "Dit attribuut zorgt ervoor dat het domein zelf niet als een domeinlid gezien wordt. Voor \"totalen\" van domeinleden dient een van toepassing zijnd domeinlid opgenomen te worden. Het totaliseren als validatie vindt plaats in een formule.",
        "en": null
    },
    "introduction_date": "2010/06/23",
    "related": "2.03.06.03",
    "error_message": {
        "nl": "Arcrole &quot;dimension-domain&quot; met @usable=&quot;false&quot; MOET concepten gebruiken in de sbr:domainItem substitutionGroup als de &quot;naar&quot; kant van de relatie",
        "en": null
    },
    "nta_rule": true,
    "pe_rule": true,
    "section": "XML Linkbase - Domeinen en Domeinleden"
}